{
  "$schema": "https://developer.microsoft.com/json-schemas/fabric/item/report/definition/visualContainer/1.6.0/schema.json",
  "name": "f318e0b66e7d20ae6350",
  "position": {
    "x": 426.66666666666663,
    "y": 75.555555555555557,
    "z": 7000,
    "height": 130,
    "width": 833.33333333333326,
    "tabOrder": 7000
  },
  "visual": {
    "visualType": "cardVisual",
    "query": {
      "queryState": {
        "Data": {
          "projections": [
            {
              "field": {
                "Aggregation": {
                  "Expression": {
                    "Column": {
                      "Expression": {
                        "SourceRef": {
                          "Entity": "dataset"
                        }
                      },
                      "Property": "EBILL"
                    }
                  },
                  "Function": 1
                }
              },
              "queryRef": "Sum(dataset.EBILL)",
              "nativeQueryRef": "Avg E-Bill",
              "displayName": "Avg E-Bill"
            },
            {
              "field": {
                "Aggregation": {
                  "Expression": {
                    "Column": {
                      "Expression": {
                        "SourceRef": {
                          "Entity": "dataset"
                        }
                      },
                      "Property": "Penalty"
                    }
                  },
                  "Function": 1
                }
              },
              "queryRef": "Sum(dataset.Penalty)",
              "nativeQueryRef": "Avg Penalty",
              "displayName": "Avg Penalty"
            },
            {
              "field": {
                "Aggregation": {
                  "Expression": {
                    "Column": {
                      "Expression": {
                        "SourceRef": {
                          "Entity": "dataset"
                        }
                      },
                      "Property": "VSAT AMC"
                    }
                  },
                  "Function": 1
                }
              },
              "queryRef": "Sum(dataset.VSAT AMC)",
              "nativeQueryRef": "Avg VSAT AMC",
              "displayName": "Avg VSAT AMC"
            },
            {
              "field": {
                "Aggregation": {
                  "Expression": {
                    "Column": {
                      "Expression": {
                        "SourceRef": {
                          "Entity": "dataset"
                        }
                      },
                      "Property": "CRA"
                    }
                  },
                  "Function": 1
                }
              },
              "queryRef": "Sum(dataset.CRA)",
              "nativeQueryRef": "Avg CRA",
              "displayName": "Avg CRA"
            },
            {
              "field": {
                "Aggregation": {
                  "Expression": {
                    "Column": {
                      "Expression": {
                        "SourceRef": {
                          "Entity": "dataset"
                        }
                      },
                      "Property": "Up Time"
                    }
                  },
                  "Function": 1
                }
              },
              "queryRef": "Sum(dataset.Up Time)",
              "nativeQueryRef": "Avg Up Time",
              "displayName": "Avg Up Time"
            }
          ]
        }
      },
      "sortDefinition": {
        "sort": [
          {
            "field": {
              "Aggregation": {
                "Expression": {
                  "Column": {
                    "Expression": {
                      "SourceRef": {
                        "Entity": "dataset"
                      }
                    },
                    "Property": "EBILL"
                  }
                },
                "Function": 1
              }
            },
            "direction": "Descending"
          }
        ],
        "isDefaultSort": true
      }
    },
    "objects": {
      "value": [
        {
          "properties": {
            "fontFamily": {
              "expr": {
                "Literal": {
                  "Value": "'''Segoe UI Semibold'', wf_segoe-ui_semibold, helvetica, arial, sans-serif'"
                }
              }
            },
            "fontSize": {
              "expr": {
                "Literal": {
                  "Value": "25D"
                }
              }
            },
            "horizontalAlignment": {
              "expr": {
                "Literal": {
                  "Value": "'center'"
                }
              }
            }
          },
          "selector": {
            "id": "default"
          }
        }
      ],
      "spacing": [
        {
          "properties": {
            "verticalSpacing": {
              "expr": {
                "Literal": {
                  "Value": "8L"
                }
              }
            }
          },
          "selector": {
            "id": "default"
          }
        }
      ],
      "layout": [
        {
          "properties": {
            "maxTiles": {
              "expr": {
                "Literal": {
                  "Value": "6L"
                }
              }
            }
          }
        }
      ],
      "fillCustom": [
        {
          "properties": {
            "show": {
              "expr": {
                "Literal": {
                  "Value": "false"
                }
              }
            }
          }
        }
      ],
      "outline": [
        {
          "properties": {
            "show": {
              "expr": {
                "Literal": {
                  "Value": "false"
                }
              }
            }
          },
          "selector": {
            "id": "default"
          }
        }
      ],
      "label": [
        {
          "properties": {
            "position": {
              "expr": {
                "Literal": {
                  "Value": "'belowValue'"
                }
              }
            }
          },
          "selector": {
            "id": "default"
          }
        },
        {
          "properties": {
            "fontSize": {
              "expr": {
                "Literal": {
                  "Value": "10D"
                }
              }
            }
          },
          "selector": {
            "metadata": "Sum(dataset.EBILL)"
          }
        },
        {
          "properties": {
            "fontSize": {
              "expr": {
                "Literal": {
                  "Value": "10D"
                }
              }
            }
          },
          "selector": {
            "metadata": "Sum(dataset.Penalty)"
          }
        },
        {
          "properties": {
            "fontSize": {
              "expr": {
                "Literal": {
                  "Value": "10D"
                }
              }
            }
          },
          "selector": {
            "metadata": "Sum(dataset.VSAT AMC)"
          }
        },
        {
          "properties": {
            "fontSize": {
              "expr": {
                "Literal": {
                  "Value": "10D"
                }
              }
            }
          },
          "selector": {
            "metadata": "Sum(dataset.CRA)"
          }
        },
        {
          "properties": {
            "fontSize": {
              "expr": {
                "Literal": {
                  "Value": "10D"
                }
              }
            }
          },
          "selector": {
            "metadata": "Sum(dataset.Up Time)"
          }
        }
      ]
    },
    "visualContainerObjects": {
      "background": [
        {
          "properties": {
            "show": {
              "expr": {
                "Literal": {
                  "Value": "false"
                }
              }
            }
          }
        }
      ]
    },
    "drillFilterOtherVisuals": true
  }
}